{
    "_id": "56c6040509d18c4c3e90a4a7",
    "guid": "105bc602-913b-489c-95f0-444cf6628614",
    "rating": 2,
    "location": "Kuala Terengganu",
    "status": {
      "text": "Vacant"
    },
    "name": "Homestay Kampung Tunku",
    "images": [
      "assets/img/homestayplaceholder.png",
      "assets/img/homestayplaceholder.png"
    ],
    "user": {
      "id": "236de81b-98fc-4af5-a5b8-44ed3cd57fa2",
      "avatar": "assets/img/mcfly.jpg",
      "name": "Mills Kane",
      "company": "BOILICON"
    },
    "description": "Adipisicing quis qui eu magna id ad occaecat magna officia laborum Lorem. Sit excepteur consectetur esse velit sunt anim commodo ex aliquip nulla aliquip esse. Sit enim exercitation sit duis tempor incididunt minim ipsum amet sit quis aute deserunt.\r\n"
  }